videotoframes/__init__.py
videotoframes/video_to_frames.py
videotoframes-1.1.5.dist-info/LICENSE
videotoframes-1.1.5.dist-info/METADATA
videotoframes-1.1.5.dist-info/WHEEL
videotoframes-1.1.5.dist-info/entry_points.txt
videotoframes-1.1.5.dist-info/top_level.txt
videotoframes-1.1.5.dist-info/RECORD
