Metadata-Version: 2.1
Name: videotoframes
Version: 1.1.5
Summary: A simple Python script to break videos into frames.
Home-page: https://github.com/brandonschabell/videotoframes
Author: Brandon Schabell
Author-email: brandonschabell@gmail.com
License: MIT
Download-URL: https://github.com/brandonschabell/videotoframes/archive/v1.1.5.tar.gz
Platform: UNKNOWN
Classifier: Development Status :: 5 - Production/Stable
Classifier: Intended Audience :: Developers
Classifier: Intended Audience :: End Users/Desktop
Classifier: Intended Audience :: Science/Research
Classifier: License :: OSI Approved :: MIT License
Classifier: Programming Language :: Python :: 3.4
Classifier: Programming Language :: Python :: 3.5
Classifier: Programming Language :: Python :: 3.6
Classifier: Programming Language :: Python :: 3.7
Classifier: Topic :: Multimedia :: Video :: Conversion
Classifier: Topic :: Utilities
Requires-Python: ~=3.4
Requires-Dist: opencv-python
Requires-Dist: tqdm
Provides-Extra: tests
Requires-Dist: pytest ; extra == 'tests'
